gustav/__init__.py
gustav/api.py
gustav/middleware.py
gustav/response.py
gustavballer/__init__.py
gustavballer/api.py
gustavballer/middleware.py
gustavballer/response.py
gustavballer-0.0.5.dist-info/METADATA
gustavballer-0.0.5.dist-info/WHEEL
gustavballer-0.0.5.dist-info/top_level.txt
gustavballer-0.0.5.dist-info/RECORD
