Metadata-Version: 2.4
Name: gustavballer
Version: 0.0.5
Summary: Gustav Baller's Python Web Framework built for learning purposes.
Author: Mark Sanders
Author-email: markdavidsanders@gmail.com
License: MIT
Classifier: Programming Language :: Python :: 3.6
Requires-Python: >=3.6.0
Requires-Dist: Jinja2==2.10.3
Requires-Dist: parse==1.12.1
Requires-Dist: requests==2.22.0
Requires-Dist: requests-wsgi-adapter==0.4.1
Requires-Dist: WebOb==1.8.5
Requires-Dist: whitenoise==4.1.4
Dynamic: author
Dynamic: author-email
Dynamic: classifier
Dynamic: description
Dynamic: description-content-type
Dynamic: license
Dynamic: requires-dist
Dynamic: requires-python
Dynamic: summary
